fate_flow/__init__.py
fate_flow/_info.py
fate_flow/fate_flow_server.py
fate_flow/fateflow.env
fate_flow/settings.py
fate_flow/adapter/__init__.py
fate_flow/adapter/_controller.py
fate_flow/adapter/_loader.py
fate_flow/adapter/bfia/__init__.py
fate_flow/adapter/bfia/runtime_config.py
fate_flow/adapter/bfia/settings.py
fate_flow/adapter/bfia/apps/__init__.py
fate_flow/adapter/bfia/apps/interconn_app.py
fate_flow/adapter/bfia/apps/platform_app.py
fate_flow/adapter/bfia/bridge/__init__.py
fate_flow/adapter/bfia/bridge/job.py
fate_flow/adapter/bfia/container/__init__.py
fate_flow/adapter/bfia/container/entrypoint/__init__.py
fate_flow/adapter/bfia/container/entrypoint/cli.py
fate_flow/adapter/bfia/container/entrypoint/runner.py
fate_flow/adapter/bfia/container/wraps/__init__.py
fate_flow/adapter/bfia/container/wraps/wraps.py
fate_flow/adapter/bfia/db/__init__.py
fate_flow/adapter/bfia/db/output.py
fate_flow/adapter/bfia/engine_storage/__init__.py
fate_flow/adapter/bfia/engine_storage/client.py
fate_flow/adapter/bfia/engine_storage/consts.py
fate_flow/adapter/bfia/engine_storage/meta.py
fate_flow/adapter/bfia/engine_storage/session.py
fate_flow/adapter/bfia/engine_storage/table.py
fate_flow/adapter/bfia/scheduler/__init__.py
fate_flow/adapter/bfia/scheduler/detector.py
fate_flow/adapter/bfia/scheduler/scheduler.py
fate_flow/adapter/bfia/translator/__init__.py
fate_flow/adapter/bfia/translator/component_spec.py
fate_flow/adapter/bfia/translator/dsl_translator.py
fate_flow/adapter/bfia/wheels/__init__.py
fate_flow/adapter/bfia/wheels/federated.py
fate_flow/adapter/bfia/wheels/job.py
fate_flow/adapter/bfia/wheels/output.py
fate_flow/adapter/bfia/wheels/parser.py
fate_flow/adapter/bfia/wheels/saver.py
fate_flow/adapter/bfia/wheels/task.py
fate_flow/apps/__init__.py
fate_flow/apps/desc.py
fate_flow/apps/desc_zh.py
fate_flow/apps/client/__init__.py
fate_flow/apps/client/client_app.py
fate_flow/apps/client/data_app.py
fate_flow/apps/client/job_app.py
testabc-1.20.0.dist-info/METADATA
testabc-1.20.0.dist-info/WHEEL
testabc-1.20.0.dist-info/entry_points.txt
testabc-1.20.0.dist-info/top_level.txt
testabc-1.20.0.dist-info/RECORD
