Metadata-Version: 2.1
Name: testabc
Version: 1.20.0
Home-page: https://fate.fedai.org/
Author: FederatedAI
Author-email: contact@FedAI.org
License: Apache-2.0 License
Keywords: federated learning scheduler
Requires-Python: >=3.8
Requires-Dist: apsw
Requires-Dist: Flask (==2.2.5)
Requires-Dist: grpcio (==1.59.3)
Requires-Dist: grpcio-tools (==1.59.3)
Requires-Dist: requests
Requires-Dist: urllib3
Requires-Dist: cachetools
Requires-Dist: filelock
Requires-Dist: pydantic (==1.10.12)
Requires-Dist: webargs
Requires-Dist: peewee
Requires-Dist: python-dotenv
Requires-Dist: pyyaml
Requires-Dist: networkx
Requires-Dist: psutil
Requires-Dist: casbin-peewee-adapter
Requires-Dist: casbin
Requires-Dist: pymysql
Requires-Dist: kazoo
Requires-Dist: shortuuid
Requires-Dist: cos-python-sdk-v5
Requires-Dist: typing-extensions
Requires-Dist: ruamel.yaml (==0.16)
Requires-Dist: boto3
Provides-Extra: eggroll
Requires-Dist: cloudpickle ; extra == 'eggroll'
Requires-Dist: lmdb ; extra == 'eggroll'
Requires-Dist: protobuf ; extra == 'eggroll'
Requires-Dist: grpcio ; extra == 'eggroll'
Requires-Dist: grpcio-tools ; extra == 'eggroll'
Provides-Extra: pulsar
Requires-Dist: pulsar-client (==2.10.2) ; extra == 'pulsar'
Provides-Extra: rabbitmq
Requires-Dist: pika (==1.2.1) ; extra == 'rabbitmq'
Provides-Extra: spark
Requires-Dist: pyspark ; extra == 'spark'
Provides-Extra: testabc
Requires-Dist: fate-flow[eggroll,pulsar,rabbitmq,spark] ; extra == 'testabc'
